Metadata-Version: 1.0
Name: ttag
Version: 0.3
Summary: translate original json data into the new json data
Home-page: UNKNOWN
Author: slc
Author-email: 1427784107@qq.com
License: UNKNOWN
Platform: UNKNOWN
